{
  "statistical_data": {
    "friends_num": 85,
    "active_num": 76,
    "error_num": 9,
    "article_num": 296,
    "last_updated_time": "2024-12-09 04:21:35"
  },
  "article_data": [
    {
      "title": "Pytorch 学习笔记6",
      "created": "2024-12-09 08:00",
      "link": "https://blog.tianli0.top/posts/2024/Pytorch6",
      "author": "Tianli",
      "avatar": "https://q2.qlogo.cn/headimg_dl?dst_uin=507249007&spec=640"
    },
    {
      "title": "2024 年 12 月 每日分享",
      "created": "2024-12-09 00:22",
      "link": "https://iui.su/192/",
      "author": "不死鸟 - 分享为王官网",
      "avatar": "https://npm.elemecdn.com/niaosu@3.3.5/logo.png"
    },
    {
      "title": "最新浏览器Flash使用指南：轻松搞定！",
      "created": "2024-12-08 22:02",
      "link": "https://gyhwd.top/archives/Jk2hw4XY",
      "author": "青竹小轩",
      "avatar": "https://cdn.qyliu.top/i/2024/04/23/662748990165a.png"
    },
    {
      "title": "2024.11.24",
      "created": "2024-12-08 20:19",
      "link": "http://ymxblog.us.kg/posts/2d1e8e7a.html",
      "author": "叶泯希",
      "avatar": "https://cdn.qyliu.top/i/2024/11/27/6747341ba9c31.webp"
    },
    {
      "title": "西江诗派韩饶二集",
      "created": "2024-12-08 19:56",
      "link": "https://www.shuge.org/view/xi_jiang_shi_pai_han_rao_er_ji/",
      "author": "书格",
      "avatar": "https://www.shuge.org/wp-content/themes/artview/images/layout/logo.png"
    },
    {
      "title": "哔哩哔哩账号备份工具，但为什么要备份 B 站账号？",
      "created": "2024-12-08 18:59",
      "link": "https://www.appinn.com/bilibili-backup-tool/",
      "author": "小众软件",
      "avatar": "https://images3.appinn.com/wp-content/uploads/2022/09/appinn-darkmode2.png"
    },
    {
      "title": "泸南往事",
      "created": "2024-12-08 17:33",
      "link": "https://maie.name/1014.html",
      "author": "流浪天下",
      "avatar": "https://img.maie.name/2016/04/cropped-favicon-32x32.png"
    },
    {
      "title": "Kekkon Yubiwa Monogatari / 婚戒物语 10-bit 1080p HEVC BDRip [Fin]",
      "created": "2024-12-08 14:40",
      "link": "https://vcb-s.com/archives/19544",
      "author": "VCB-Studio",
      "avatar": "https://vcb-s.com/wp-content/themes/zanblog2_1_0/ui/images/logo-d-2.svg"
    },
    {
      "title": "去掉UkeySoft Screen Recorder 8.0.0 弹窗",
      "created": "2024-12-08 10:12",
      "link": "https://h4ck.org.cn/2024/12/18738",
      "author": "obaby",
      "avatar": "https://cdn.qyliu.top/i/2024/04/15/661d443b5359c.png"
    },
    {
      "title": "瑞幸深烘果然很苦",
      "created": "2024-12-08 09:08",
      "link": "http://www.xlanda.net/posts/21025",
      "author": "我的天",
      "avatar": null
    },
    {
      "title": "#双12#狗云(dogyun)，云服务器，新开弹性云7折/经典云8折，独服优惠100元/幸运大转盘抽5折优惠",
      "created": "2024-12-08 08:47",
      "link": "https://www.daniao.org/24622.html",
      "author": "大鸟博客",
      "avatar": "https://cravatar.cn/avatar/0755f4f3b61196d7765cc9f080c56b0f?d=mp&s=80"
    },
    {
      "title": "Ephemeralis-Weekly（14）：泡沫箱里的宣纸",
      "created": "2024-12-08 08:00",
      "link": "https://www.yoghurtlee.com/weekly-14/",
      "author": "Chlorine",
      "avatar": "https://cdn.qyliu.top/i/2024/08/07/66b2daf9ab79f.webp"
    },
    {
      "title": "ME老师达芬奇调色课程_摩吉影像",
      "created": "2024-12-08 07:43",
      "link": "https://hapgpt.com/archives/nszqUWu0",
      "author": "小莫分享",
      "avatar": "https://cravatar.cn/avatar/8f66161f3fd90add0e967cfa8843bc04?d=mp&s=80"
    },
    {
      "title": "「今日早报」 2024年12月8日, 农历十一月初八, 星期日",
      "created": "2024-12-08 02:10",
      "link": "https://www.sammery.com/archives/5865.html",
      "author": "沙漠渔溏",
      "avatar": "https://www.sammery.com/favicon.ico"
    },
    {
      "title": "奇奇怪怪的",
      "created": "2024-12-08 00:00",
      "link": "https://blog.xxfer.cn/posts/c61e8224.html",
      "author": "小李同学",
      "avatar": "https://cdn.qyliu.top/i/2024/11/28/6747439e8f0f9.webp"
    },
    {
      "title": "【也闲谈·十四】草蛇灰线伏脉千里",
      "created": "2024-12-07 22:10",
      "link": "http://www.qncd.com/?p=10963",
      "author": "尺宅杂记",
      "avatar": "http://www.qncd.com/wp-content/uploads/2024/07/0716.jpg"
    },
    {
      "title": "风记得的第1651天星辰：两万具尸体、两年前解封的第二天感染、两天前是她轻生的第二天",
      "created": "2024-12-07 22:10",
      "link": "https://www.thyuu.com/79168",
      "author": "风记星辰",
      "avatar": "https://cdn.qyliu.top/i/2024/08/04/66af2d2430f68.webp"
    },
    {
      "title": "媳妇做课件太难，程序员熬夜写App：免费的音频转换器",
      "created": "2024-12-07 19:51",
      "link": "https://www.appinn.com/audio-converter-mp3-extractor/",
      "author": "小众软件",
      "avatar": "https://images3.appinn.com/wp-content/uploads/2022/09/appinn-darkmode2.png"
    },
    {
      "title": "zgovps：美国便宜VPS补货，$15/年，1核1G/20G硬盘/1G带宽@2T流量/国际线路",
      "created": "2024-12-07 15:34",
      "link": "https://www.daniao.org/24619.html",
      "author": "大鸟博客",
      "avatar": "https://cravatar.cn/avatar/0755f4f3b61196d7765cc9f080c56b0f?d=mp&s=80"
    },
    {
      "title": "彼方的她：一场跨越时空的对话，一段孤寂宇宙的回响",
      "created": "2024-12-07 15:25",
      "link": "http://blog.awaae001.top/posts/23435.html",
      "author": "呓语梦轩",
      "avatar": "https://cdn.qyliu.top/i/2024/03/30/660769346d538.jpg"
    },
    {
      "title": "lightlayer：泰国曼谷原生IP VPS测评分享",
      "created": "2024-12-07 13:18",
      "link": "https://www.daniao.org/24602.html",
      "author": "大鸟博客",
      "avatar": "https://cravatar.cn/avatar/0755f4f3b61196d7765cc9f080c56b0f?d=mp&s=80"
    },
    {
      "title": "5️⃣启动公众号引流",
      "created": "2024-12-07 12:06",
      "link": "https://blog.study996.cn/archives/980d931/",
      "author": "寻梦城 - 寻找失落之城",
      "avatar": "https://q2.qlogo.cn/headimg_dl?dst_uin=2071916845&spec=640"
    },
    {
      "title": "实现躺平自由！胶囊型投影仪Anker Nebula Capsule 3 Laser使用体验",
      "created": "2024-12-07 11:57",
      "link": "https://www.wikimoe.com/post/40qscgfz",
      "author": "维基萌",
      "avatar": "https://www.wikimoe.com/upload/siteImg/siteFavicon.webp"
    },
    {
      "title": "4️⃣免费下载无损音乐的网站",
      "created": "2024-12-07 11:03",
      "link": "https://blog.study996.cn/archives/9f1faa5d/",
      "author": "寻梦城 - 寻找失落之城",
      "avatar": "https://q2.qlogo.cn/headimg_dl?dst_uin=2071916845&spec=640"
    },
    {
      "title": "双12 特惠！Bartender 5 限时 8 折，最好的 macOS 菜单栏图标隐藏工具",
      "created": "2024-12-07 10:48",
      "link": "https://www.appinn.com/bartender-5-lizhi/",
      "author": "小众软件",
      "avatar": "https://images3.appinn.com/wp-content/uploads/2022/09/appinn-darkmode2.png"
    },
    {
      "title": "新入手白色陶瓷滤杯",
      "created": "2024-12-07 09:17",
      "link": "http://www.xlanda.net/posts/21023",
      "author": "我的天",
      "avatar": null
    },
    {
      "title": "月度随笔|2024-11",
      "created": "2024-12-07 08:00",
      "link": "https://blog.xing-ye.top/posts/9cc0e15/",
      "author": "XINGYE",
      "avatar": "https://cdn.qyliu.top/i/2024/05/18/6648b84c682e1.png"
    },
    {
      "title": "「今日早报」 2024年12月7日, 农历十一月初七, 星期六",
      "created": "2024-12-07 02:10",
      "link": "https://www.sammery.com/archives/5864.html",
      "author": "沙漠渔溏",
      "avatar": "https://www.sammery.com/favicon.ico"
    },
    {
      "title": "SimpleMindMap – 开源、功能完整的思维导图工具[跨平台/Web]，更新 obsidian 插件",
      "created": "2024-12-06 23:14",
      "link": "https://www.appinn.com/simplemindmap/",
      "author": "小众软件",
      "avatar": "https://images3.appinn.com/wp-content/uploads/2022/09/appinn-darkmode2.png"
    },
    {
      "title": "互联网越来越孤岛化了",
      "created": "2024-12-06 20:37",
      "link": "https://www.peterjxl.com/Internet/isolated/",
      "author": "从 01 开始",
      "avatar": "https://image.peterjxl.com/blog/re0.jpg"
    },
    {
      "title": "Spotify2024年度总结",
      "created": "2024-12-06 19:34",
      "link": "https://www.vlo.cc/notes/18",
      "author": "华岁云小屋",
      "avatar": "https://mx.vlo.cc/api/v2/objects/avatar/t3vpbdbvpmo0o3eduy.jpg"
    },
    {
      "title": "lightlayer：德国法兰克福原生IP VPS测评分享",
      "created": "2024-12-06 18:19",
      "link": "https://www.daniao.org/24584.html",
      "author": "大鸟博客",
      "avatar": "https://cravatar.cn/avatar/0755f4f3b61196d7765cc9f080c56b0f?d=mp&s=80"
    },
    {
      "title": "Linux tmux 基础使用教程",
      "created": "2024-12-06 18:01",
      "link": "https://www.zouht.com/3846.html",
      "author": "ChrisKim",
      "avatar": "https://cdn.qyliu.top/i/2024/06/27/667d880789765.webp"
    },
    {
      "title": "WeekNote 2024-49",
      "created": "2024-12-06 16:44",
      "link": "https://hp-l.github.io/2024/12/06/164452/",
      "author": "子书承宇",
      "avatar": "https://cdn.qyliu.top/i/2024/11/11/67321d6dcee8e.webp"
    },
    {
      "title": "广西南宁一月游",
      "created": "2024-12-06 16:39",
      "link": "https://www.aimiliy.top/posts/a4f09b44.html",
      "author": "MuXiaoChen",
      "avatar": "https://cdn.qyliu.top/i/2024/09/20/66ed45792c171.webp"
    },
    {
      "title": "TLDRify – 标记网页内特定文字内容，并转换为短链接",
      "created": "2024-12-06 15:28",
      "link": "https://www.appinn.com/tldrify/",
      "author": "小众软件",
      "avatar": "https://images3.appinn.com/wp-content/uploads/2022/09/appinn-darkmode2.png"
    },
    {
      "title": "CstoneCloud：美国9929住宅双ISP，7.5折，49.5元/月，1核1G内存/20G SSD/100M@1T流量",
      "created": "2024-12-06 15:15",
      "link": "https://www.daniao.org/24582.html",
      "author": "大鸟博客",
      "avatar": "https://cravatar.cn/avatar/0755f4f3b61196d7765cc9f080c56b0f?d=mp&s=80"
    },
    {
      "title": "Macross Delta / 超时空要塞Δ 10-bit 1080p HEVC BDRip [TV + MOVIE Reseed + MOVIE Fin]",
      "created": "2024-12-06 14:10",
      "link": "https://vcb-s.com/archives/19531",
      "author": "VCB-Studio",
      "avatar": "https://vcb-s.com/wp-content/themes/zanblog2_1_0/ui/images/logo-d-2.svg"
    },
    {
      "title": "Quick Picture Viewer看图",
      "created": "2024-12-06 13:39",
      "link": "https://iui.su/1455/",
      "author": "不死鸟 - 分享为王官网",
      "avatar": "https://npm.elemecdn.com/niaosu@3.3.5/logo.png"
    },
    {
      "title": "ppt",
      "created": "2024-12-06 13:04",
      "link": "http://xlwlgzs.com/archives/ppt",
      "author": "小陆yaの博客",
      "avatar": "https://cdn.qyliu.top/i/2024/08/18/66c1b740ad40d.webp"
    },
    {
      "title": "通过cloudflare加速网站时，防止源站被直接解析访问的高级用法",
      "created": "2024-12-06 12:23",
      "link": "https://simonsu.cn/p/1045/",
      "author": "SimonSu",
      "avatar": "https://simonsu.cn/static/images/qcode.png"
    },
    {
      "title": "对付深烘挂耳",
      "created": "2024-12-06 10:43",
      "link": "http://www.xlanda.net/posts/21020",
      "author": "我的天",
      "avatar": null
    },
    {
      "title": "科技爱好者周刊（第 328 期）：AI 模型不是一门好生意",
      "created": "2024-12-06 08:18",
      "link": "http://www.ruanyifeng.com/blog/2024/12/weekly-issue-328.html",
      "author": "阮一峰的网络日志",
      "avatar": "https://www.ruanyifeng.com/blog/images/person2_s.jpg"
    },
    {
      "title": "Pytorch 学习笔记5",
      "created": "2024-12-06 08:00",
      "link": "https://blog.tianli0.top/posts/2024/Pytorch5",
      "author": "Tianli",
      "avatar": "https://cdn.qyliu.top/i/2024/04/06/66116950412cc.png"
    },
    {
      "title": "人物事迹十二帧册",
      "created": "2024-12-06 07:00",
      "link": "https://www.shuge.org/view/ren_wu_shi_ji_shi_er_zheng_ce/",
      "author": "书格",
      "avatar": "https://www.shuge.org/wp-content/themes/artview/images/layout/logo.png"
    },
    {
      "title": "「今日早报」 2024年12月6日, 农历十一月初六, 星期五",
      "created": "2024-12-06 01:35",
      "link": "https://www.sammery.com/archives/5863.html",
      "author": "沙漠渔溏",
      "avatar": "https://www.sammery.com/favicon.ico"
    },
    {
      "title": "初识法语键盘",
      "created": "2024-12-05 22:57",
      "link": "https://hp-l.github.io/2024/12/05/225718/",
      "author": "子书承宇",
      "avatar": "https://cdn.qyliu.top/i/2024/11/11/67321d6dcee8e.webp"
    },
    {
      "title": "网站被恶意扫描时的反击魔法之一：用gzip压缩炸弹给恶意请求埋地雷",
      "created": "2024-12-05 18:43",
      "link": "https://simonsu.cn/p/1098/",
      "author": "SimonSu",
      "avatar": "https://simonsu.cn/static/images/qcode.png"
    },
    {
      "title": "送别",
      "created": "2024-12-05 13:23",
      "link": "https://h4ck.org.cn/2024/12/18723",
      "author": "obaby",
      "avatar": "https://cdn.qyliu.top/i/2024/04/15/661d443b5359c.png"
    },
    {
      "title": "Edomae Elf / 江户前精灵 10-bit 1080p HEVC BDRip [Fin]",
      "created": "2024-12-05 12:24",
      "link": "https://vcb-s.com/archives/19526",
      "author": "VCB-Studio",
      "avatar": "https://vcb-s.com/wp-content/themes/zanblog2_1_0/ui/images/logo-d-2.svg"
    },
    {
      "title": "《秋之回忆》系列最新作《秋之回忆 双想 ～Not always true～》的发售日定在了2025年...",
      "created": "2024-12-05 12:18",
      "link": "https://www.wikimoe.com/post/t4wbk47h",
      "author": "维基萌",
      "avatar": "https://www.wikimoe.com/upload/siteImg/siteFavicon.webp"
    },
    {
      "title": "人生三十或立或已",
      "created": "2024-12-05 10:55",
      "link": "https://www.thyuu.com/79173",
      "author": "风记星辰",
      "avatar": "https://cdn.qyliu.top/i/2024/08/04/66af2d2430f68.webp"
    },
    {
      "title": "无限利用孩子卡bug的女人",
      "created": "2024-12-05 10:35",
      "link": "https://xingbianren.cn/post/285.html",
      "author": "刑辩人在路上",
      "avatar": "https://xingbianren.cn/zb_users/upload/2023/05/202305231684818664504571.png"
    },
    {
      "title": "第一次四六冲",
      "created": "2024-12-05 08:16",
      "link": "http://www.xlanda.net/posts/21017",
      "author": "我的天",
      "avatar": null
    },
    {
      "title": "「今日早报」 2024年12月5日, 农历十一月初五, 星期四",
      "created": "2024-12-05 02:10",
      "link": "https://www.sammery.com/archives/5862.html",
      "author": "沙漠渔溏",
      "avatar": "https://www.sammery.com/favicon.ico"
    },
    {
      "title": "转载：祝贺春节申遗成功！",
      "created": "2024-12-05 00:10",
      "link": "https://www.iczrx.cn/archives/134/",
      "author": "晚夜",
      "avatar": "https://cdn.qyliu.top/i/2024/10/06/6702aa07d5bd8.webp"
    },
    {
      "title": "他乡纵有当头月，不及家乡一盏灯",
      "created": "2024-12-04 18:30",
      "link": "http://ymxblog.us.kg/posts/63e1fc9e.html",
      "author": "叶泯希",
      "avatar": "https://cdn.qyliu.top/i/2024/11/27/6747341ba9c31.webp"
    },
    {
      "title": "3️⃣简洁的在线生成封面 Mini-Cover",
      "created": "2024-12-04 17:59",
      "link": "https://blog.study996.cn/archives/c7746d97/",
      "author": "寻梦城 - 寻找失落之城",
      "avatar": "https://q2.qlogo.cn/headimg_dl?dst_uin=2071916845&spec=640"
    },
    {
      "title": "可视TV Max双端及多仓接口：可视TV Max 电视版2.0.8、可视TV手机版1.0.4",
      "created": "2024-12-04 17:41",
      "link": "https://www.wangdu.site/software/dianshihezi/2177.html",
      "author": "文武科技柜",
      "avatar": "https://www.wangdu.site/wp-content/uploads/2021/08/favicon.png"
    },
    {
      "title": "Mac上使用Drawthings的Flux模型进行扩图、补图",
      "created": "2024-12-04 17:21",
      "link": "https://blog.zhheo.com/p/5vi77cg0.html",
      "author": "张洪Heo",
      "avatar": "https://cdn.qyliu.top/i/2024/08/04/66af2e22827be.webp"
    },
    {
      "title": "【共读记·廿四】人生如负重行远",
      "created": "2024-12-04 16:45",
      "link": "http://www.qncd.com/?p=10958",
      "author": "尺宅杂记",
      "avatar": "http://www.qncd.com/wp-content/uploads/2024/07/0716.jpg"
    },
    {
      "title": "2️⃣hexo防止被镜像-省流版",
      "created": "2024-12-04 15:14",
      "link": "https://blog.study996.cn/archives/baffd918/",
      "author": "寻梦城 - 寻找失落之城",
      "avatar": "https://q2.qlogo.cn/headimg_dl?dst_uin=2071916845&spec=640"
    },
    {
      "title": "咖啡粉坑",
      "created": "2024-12-04 15:07",
      "link": "http://www.xlanda.net/posts/21015",
      "author": "我的天",
      "avatar": null
    },
    {
      "title": "电视直播大全",
      "created": "2024-12-04 13:40",
      "link": "https://iui.su/3154/",
      "author": "不死鸟 - 分享为王官网",
      "avatar": "https://npm.elemecdn.com/niaosu@3.3.5/logo.png"
    },
    {
      "title": "网页在线工具汇总",
      "created": "2024-12-04 13:12",
      "link": "https://iui.su/1492/",
      "author": "不死鸟 - 分享为王官网",
      "avatar": "https://npm.elemecdn.com/niaosu@3.3.5/logo.png"
    },
    {
      "title": "SCDN 放弃 DDNS 回源 — IP 地址回源更新工具 V1.0【开源】",
      "created": "2024-12-04 11:03",
      "link": "https://h4ck.org.cn/2024/12/18710",
      "author": "obaby",
      "avatar": "https://cdn.qyliu.top/i/2024/04/15/661d443b5359c.png"
    },
    {
      "title": "Mac使用rsync实现本地文件夹同步到服务器，提交编译好的静态站点，增量提交网站",
      "created": "2024-12-04 10:48",
      "link": "https://blog.zhheo.com/p/3anvspa5.html",
      "author": "张洪Heo",
      "avatar": "https://cdn.qyliu.top/i/2024/08/04/66af2e22827be.webp"
    },
    {
      "title": "Pytorch 学习笔记3",
      "created": "2024-12-04 08:00",
      "link": "https://blog.tianli0.top/posts/2024/Pytorch3",
      "author": "Tianli",
      "avatar": "https://cdn.qyliu.top/i/2024/04/06/66116950412cc.png"
    },
    {
      "title": "Pytorch 学习笔记4",
      "created": "2024-12-04 08:00",
      "link": "https://blog.tianli0.top/posts/2024/Pytorch4",
      "author": "Tianli",
      "avatar": "https://cdn.qyliu.top/i/2024/04/06/66116950412cc.png"
    },
    {
      "title": "软著申请源代码整合脚本",
      "created": "2024-12-04 02:31",
      "link": "https://blog.randench.cn/posts/59970/",
      "author": "RE Blog",
      "avatar": "https://cdn.qyliu.top/i/2024/11/19/673cb26cbdb2e.webp"
    },
    {
      "title": "「今日早报」 2024年12月4日, 农历十一月初四, 星期三",
      "created": "2024-12-04 02:05",
      "link": "https://www.sammery.com/archives/5861.html",
      "author": "沙漠渔溏",
      "avatar": "https://www.sammery.com/favicon.ico"
    },
    {
      "title": "QQNT插件LiteLoader食用指南",
      "created": "2024-12-04 02:00",
      "link": "https://blog.ciraos.top/posts/QQPluginNote",
      "author": "葱苓sama",
      "avatar": "https://cdn.qyliu.top/i/2024/05/03/663458df4e6f0.png"
    },
    {
      "title": "基于 llama.cpp 实现高性能本地大模型推理",
      "created": "2024-12-04 00:57",
      "link": "https://www.zouht.com/3835.html",
      "author": "ChrisKim",
      "avatar": "https://cdn.qyliu.top/i/2024/06/27/667d880789765.webp"
    },
    {
      "title": "【转载】《刮掉胡子的我与捡到的女高中生》",
      "created": "2024-12-03 23:31",
      "link": "https://www.himiku.com/archives/higehero.html",
      "author": "初之音",
      "avatar": "https://cravatar.cn/avatar/2fc4cf3560ff5a1cc64ea029896ab235?s=400"
    },
    {
      "title": "【家塾记·十一】半小时讲完《秋声赋》",
      "created": "2024-12-03 21:00",
      "link": "http://www.qncd.com/?p=10955",
      "author": "尺宅杂记",
      "avatar": "http://www.qncd.com/wp-content/uploads/2024/07/0716.jpg"
    },
    {
      "title": "亚马逊黑色星期五打折买了7样商品，结果后台显示亚马逊给我打成了8个包...为什么会是8个包呢？其中有...",
      "created": "2024-12-03 18:16",
      "link": "https://www.wikimoe.com/post/517z4d1h",
      "author": "维基萌",
      "avatar": "https://www.wikimoe.com/upload/siteImg/siteFavicon.webp"
    },
    {
      "title": "1️⃣各大 Emby 公益服",
      "created": "2024-12-03 17:34",
      "link": "https://blog.study996.cn/archives/6a2818c9/",
      "author": "寻梦城 - 寻找失落之城",
      "avatar": "https://q2.qlogo.cn/headimg_dl?dst_uin=2071916845&spec=640"
    },
    {
      "title": "详细记录通过Qt在线安装器安装Qt5.15系列版本",
      "created": "2024-12-03 14:51",
      "link": "https://www.52txr.cn/2024/Qt515install.html",
      "author": "陶小桃Blog",
      "avatar": "https://z1.ax1x.com/2023/01/12/pSuDn6H.png"
    },
    {
      "title": "汉王扫描王",
      "created": "2024-12-03 14:27",
      "link": "https://iui.su/3620/",
      "author": "不死鸟 - 分享为王官网",
      "avatar": "https://npm.elemecdn.com/niaosu@3.3.5/logo.png"
    },
    {
      "title": "Alist如何添加Ubuntu服务器的文件夹，给服务器添加上传SFTP的账号并授予访问权限",
      "created": "2024-12-03 14:22",
      "link": "https://blog.zhheo.com/p/o6jvfadz.html",
      "author": "张洪Heo",
      "avatar": "https://cdn.qyliu.top/i/2024/08/04/66af2e22827be.webp"
    },
    {
      "title": "Tensei Kizoku no Isekai Boukenroku / 转生贵族的异世界冒险录 ～不知自重的诸神的使徒～ 10-bit 1080p HEVC BDRip [Fin]",
      "created": "2024-12-03 13:35",
      "link": "https://vcb-s.com/archives/19502",
      "author": "VCB-Studio",
      "avatar": "https://vcb-s.com/wp-content/themes/zanblog2_1_0/ui/images/logo-d-2.svg"
    },
    {
      "title": "有线音箱改无线蓝牙音箱",
      "created": "2024-12-03 13:00",
      "link": "https://xiangming.site/901.html",
      "author": "湘铭",
      "avatar": "https://cdn.qyliu.top/i/2024/04/19/6622928fc416c.png"
    },
    {
      "title": "解决安卓端 Kindle APP无法与 Kindle 硬件同步",
      "created": "2024-12-03 12:50",
      "link": "https://hp-l.github.io/2024/12/03/125011/",
      "author": "子书承宇",
      "avatar": "https://cdn.qyliu.top/i/2024/11/11/67321d6dcee8e.webp"
    },
    {
      "title": "老徐的这几年：从“良家子”到“上访户”",
      "created": "2024-12-03 12:41",
      "link": "https://xingbianren.cn/post/284.html",
      "author": "刑辩人在路上",
      "avatar": "https://xingbianren.cn/zb_users/upload/2023/05/202305231684818664504571.png"
    },
    {
      "title": "一觉醒来天塌了，博客半夜被刷了2个亿的请求",
      "created": "2024-12-03 10:05",
      "link": "https://www.52txr.cn/2024/cc2yi.html",
      "author": "陶小桃Blog",
      "avatar": "https://z1.ax1x.com/2023/01/12/pSuDn6H.png"
    },
    {
      "title": "Pytorch 学习笔记1",
      "created": "2024-12-03 08:00",
      "link": "https://blog.tianli0.top/posts/2024/Pytorch1",
      "author": "Tianli",
      "avatar": "https://cdn.qyliu.top/i/2024/04/06/66116950412cc.png"
    },
    {
      "title": "Pytorch 学习笔记2",
      "created": "2024-12-03 08:00",
      "link": "https://blog.tianli0.top/posts/2024/Pytorch2",
      "author": "Tianli",
      "avatar": "https://cdn.qyliu.top/i/2024/04/06/66116950412cc.png"
    },
    {
      "title": "朋友的 Vivado 和 Modelsim 装上了吗",
      "created": "2024-12-03 08:00",
      "link": "https://blog.zhilu.cyou/2024/vivado-modelsim-rescue",
      "author": "纸鹿本鹿",
      "avatar": "https://cdn.qyliu.top/i/2024/06/02/665c869ded7cd.png"
    },
    {
      "title": "rehype-autolink-headings Simple Version",
      "created": "2024-12-03 08:00",
      "link": "https://cworld0.com/blog/rehype-autolink-headings",
      "author": "CWorld",
      "avatar": "https://cdn.qyliu.top/i/2024/11/18/673b5d44a04dd.webp"
    },
    {
      "title": "Git摘樱桃拆分commit进行提交",
      "created": "2024-12-03 00:00",
      "link": "https://www.gan1ser.top/post/41115324.html",
      "author": "GanSer",
      "avatar": "https://cdn.qyliu.top/i/2024/04/29/662fbba91addc.png"
    },
    {
      "title": "解决罗技 G304 鼠标按键连点问题，续命成功！",
      "created": "2024-12-02 22:32",
      "link": "https://www.shephe.com/post/g304-replace-micro-switch/",
      "author": "Kevin's Space",
      "avatar": "https://cravatar.cn/avatar/cbbe656c7bb46772f589c9b18a7c747e?s=160&d=robohash&r=g%202x"
    },
    {
      "title": "利用 Termux 让安卓手机成为专属家庭服务器",
      "created": "2024-12-02 21:58",
      "link": "https://talen.top/posts/2e3499c7/",
      "author": "M.Talen",
      "avatar": "https://cdn.qyliu.top/i/2024/05/23/664eda97bdec6.png"
    },
    {
      "title": "AI 应用无代码开发教程：工作流模式详解",
      "created": "2024-12-02 18:39",
      "link": "http://www.ruanyifeng.com/blog/2024/12/no-code-ai-tutorial.html",
      "author": "阮一峰的网络日志",
      "avatar": "https://www.ruanyifeng.com/blog/images/person2_s.jpg"
    },
    {
      "title": "PixPin上手：Mac上强大免费的截图、录屏工具，一个都搞定",
      "created": "2024-12-02 17:48",
      "link": "https://blog.zhheo.com/p/io1i02p6.html",
      "author": "张洪Heo",
      "avatar": "https://cdn.qyliu.top/i/2024/08/04/66af2e22827be.webp"
    },
    {
      "title": "深秋天台山国清寺怀古",
      "created": "2024-12-02 16:42",
      "link": "https://maie.name/1013.html",
      "author": "流浪天下",
      "avatar": "https://img.maie.name/2016/04/cropped-favicon-32x32.png"
    },
    {
      "title": "【共读记·廿三】放弃挣扎",
      "created": "2024-12-02 16:30",
      "link": "http://www.qncd.com/?p=10950",
      "author": "尺宅杂记",
      "avatar": "http://www.qncd.com/wp-content/uploads/2024/07/0716.jpg"
    },
    {
      "title": "简单完成4个任务，即可领取通义灵码限量版超大鼠标垫",
      "created": "2024-12-02 15:48",
      "link": "https://www.wangdu.site/fuliyouhui/2175.html",
      "author": "文武科技柜",
      "avatar": "https://www.wangdu.site/wp-content/uploads/2021/08/favicon.png"
    },
    {
      "title": "周末时光：八音盒和烤鱼",
      "created": "2024-12-02 15:19",
      "link": "https://vjo.cc/1569",
      "author": "刘郎阁",
      "avatar": "https://cdn.qyliu.top/i/2024/04/19/66229406a68df.png"
    },
    {
      "title": "12月",
      "created": "2024-12-02 15:13",
      "link": "https://lanxing.net/archives/227/",
      "author": "揽星",
      "avatar": "https://cdn.qyliu.top/i/2024/04/07/6612410571110.png"
    },
    {
      "title": "双城记",
      "created": "2024-12-02 11:11",
      "link": "https://h4ck.org.cn/2024/12/18679",
      "author": "obaby",
      "avatar": "https://cdn.qyliu.top/i/2024/04/15/661d443b5359c.png"
    },
    {
      "title": "我选择了红米K80",
      "created": "2024-12-02 10:39",
      "link": "https://qq.mba/197.html",
      "author": "满心记",
      "avatar": "https://cdn.qyliu.top/i/2024/08/04/66af31bec75a0.webp"
    },
    {
      "title": "给域名添加CAA记录，提升HTTPS的安全性",
      "created": "2024-12-02 10:25",
      "link": "https://simonsu.cn/p/1097/",
      "author": "SimonSu",
      "avatar": "https://simonsu.cn/static/images/qcode.png"
    },
    {
      "title": "Project list / 作品项目列表",
      "created": "2024-12-02 03:29",
      "link": "https://vcb-s.com/archives/138",
      "author": "VCB-Studio",
      "avatar": "https://vcb-s.com/wp-content/themes/zanblog2_1_0/ui/images/logo-d-2.svg"
    },
    {
      "title": "1Panel 专业版低价租用",
      "created": "2024-12-02 00:00",
      "link": "https://dusays.com/774/",
      "author": "杜老师说",
      "avatar": "https://cdn.qyliu.top/i/2024/08/04/66af33a4d6643.webp"
    },
    {
      "title": "写在24年的年底",
      "created": "2024-12-01 23:53",
      "link": "https://www.lxink.cn/posts/acab6032.html",
      "author": "凉心",
      "avatar": "https://cdn.qyliu.top/i/2024/05/24/66500d797ac38.png"
    },
    {
      "title": "月夜杂记241130期 | 年末闲谈",
      "created": "2024-12-01 23:13",
      "link": "https://www.iczrx.cn/archives/133/",
      "author": "晚夜",
      "avatar": "https://cdn.qyliu.top/i/2024/10/06/6702aa07d5bd8.webp"
    },
    {
      "title": "特地跑到秋叶原就是为了看《点兔》联动，纱路真的太可爱了！",
      "created": "2024-12-01 18:19",
      "link": "https://www.wikimoe.com/post/40o324v4",
      "author": "维基萌",
      "avatar": "https://www.wikimoe.com/upload/siteImg/siteFavicon.webp"
    },
    {
      "title": "24年11月小结",
      "created": "2024-12-01 17:00",
      "link": "https://koxiuqiu.cn/2024/12y1d1/",
      "author": "朽丘博",
      "avatar": "https://cdn.qyliu.top/i/2024/08/20/66c41c9c45e2a.webp"
    },
    {
      "title": "研究性学习调查问卷",
      "created": "2024-12-01 14:00",
      "link": "https://h.liyy.us.kg/2024/12/01/yjx-study/",
      "author": "茗辰原",
      "avatar": "https://cdn.qyliu.top/i/2024/04/21/66249e0a775f8.png"
    },
    {
      "title": "婚礼与人像修图全流程解析：从原片到惊艳成品",
      "created": "2024-12-01 11:48",
      "link": "https://www.shephe.com/photography/photoshop-portrait-retouching/",
      "author": "Kevin's Space",
      "avatar": "https://cravatar.cn/avatar/cbbe656c7bb46772f589c9b18a7c747e?s=160&d=robohash&r=g%202x"
    },
    {
      "title": "AI挑唆人类自杀?",
      "created": "2024-12-01 11:00",
      "link": "https://h.liyy.us.kg/2024/12/01/aitiaosuo/",
      "author": "茗辰原",
      "avatar": "https://cdn.qyliu.top/i/2024/04/21/66249e0a775f8.png"
    },
    {
      "title": "NVM管理Node.js版本切换",
      "created": "2024-12-01 08:00",
      "link": "https://blog.xing-ye.top/posts/438a2e37/",
      "author": "XINGYE",
      "avatar": "https://cdn.qyliu.top/i/2024/05/18/6648b84c682e1.png"
    },
    {
      "title": "2024 年 11 月记",
      "created": "2024-12-01 05:24",
      "link": "https://www.peterjxl.com/2024/11/",
      "author": "从 01 开始",
      "avatar": "https://image.peterjxl.com/blog/re0.jpg"
    },
    {
      "title": "防止网站被镜像的若干措施及反制手段",
      "created": "2024-12-01 04:12",
      "link": "https://blog.uuanqin.top/p/7d2de43e/",
      "author": "半方池水",
      "avatar": "https://cdn.qyliu.top/i/2024/04/14/661bf5b9d3d5c.png"
    },
    {
      "title": "高颜值的私人书签导航-OneNav | Docker安装",
      "created": "2024-11-30 22:29",
      "link": "https://www.iczrx.cn/archives/132/",
      "author": "晚夜",
      "avatar": "https://cdn.qyliu.top/i/2024/10/06/6702aa07d5bd8.webp"
    },
    {
      "title": "【也闲谈·十三】帝尧杀心起，鲧就必须死",
      "created": "2024-11-30 22:14",
      "link": "http://www.qncd.com/?p=10944",
      "author": "尺宅杂记",
      "avatar": "http://www.qncd.com/wp-content/uploads/2024/07/0716.jpg"
    },
    {
      "title": "Vercel+Aiven 自建Umami统计",
      "created": "2024-11-30 15:18",
      "link": "http://ymxblog.us.kg/posts/f4576f3d.html",
      "author": "叶泯希",
      "avatar": "https://cdn.qyliu.top/i/2024/11/27/6747341ba9c31.webp"
    },
    {
      "title": "《交响乐之雨》Switch版，将于2024年12月12日发售。限定版售价7480日元（约362人民币...",
      "created": "2024-11-30 13:49",
      "link": "https://www.wikimoe.com/post/5q473zqp",
      "author": "维基萌",
      "avatar": "https://www.wikimoe.com/upload/siteImg/siteFavicon.webp"
    },
    {
      "title": "本站进一步完善了用户系统，欢迎使用 & 测试",
      "created": "2024-11-30 10:28",
      "link": "https://www.shephe.com/website/%e5%bc%ba%e5%88%b6%e7%99%bb%e5%bd%95/",
      "author": "Kevin's Space",
      "avatar": "https://cravatar.cn/avatar/cbbe656c7bb46772f589c9b18a7c747e?s=160&d=robohash&r=g%202x"
    },
    {
      "title": "学到凌晨四五点的研究生就是容易胡思乱想",
      "created": "2024-11-29 21:56",
      "link": "https://www.52txr.cn/2024/am45.html",
      "author": "陶小桃Blog",
      "avatar": "https://z1.ax1x.com/2023/01/12/pSuDn6H.png"
    },
    {
      "title": "十一家注孙子",
      "created": "2024-11-29 17:28",
      "link": "https://www.shuge.org/view/shi_yi_jia_zhu_sun_zi/",
      "author": "书格",
      "avatar": "https://www.shuge.org/wp-content/themes/artview/images/layout/logo.png"
    },
    {
      "title": "WeekNote 2024-48",
      "created": "2024-11-29 16:44",
      "link": "https://hp-l.github.io/2024/11/29/164452/",
      "author": "子书承宇",
      "avatar": "https://cdn.qyliu.top/i/2024/11/11/67321d6dcee8e.webp"
    },
    {
      "title": "Hexo教程(三) Web前端“三剑客”",
      "created": "2024-11-29 13:43",
      "link": "https://blog.elykia.cn/posts/20.html",
      "author": "Elykia",
      "avatar": "https://cdn.qyliu.top/i/2024/10/13/670b53452abec.webp"
    },
    {
      "title": "宝塔Nginx反代上游服务器不支持HTTP3，如何启用HTTP3",
      "created": "2024-11-29 12:59",
      "link": "https://blog.zhheo.com/p/6zuz70vr.html",
      "author": "张洪Heo",
      "avatar": "https://cdn.qyliu.top/i/2024/08/04/66af2e22827be.webp"
    },
    {
      "title": "科技爱好者周刊（第 327 期）：没有链接的互联网",
      "created": "2024-11-29 08:17",
      "link": "http://www.ruanyifeng.com/blog/2024/11/weekly-issue-327.html",
      "author": "阮一峰的网络日志",
      "avatar": "https://www.ruanyifeng.com/blog/images/person2_s.jpg"
    },
    {
      "title": "idea设置代码补全不区分（忽略）大小写",
      "created": "2024-11-29 00:07",
      "link": "https://www.liuyg.cn/archives/ideashe-zhi-dai-ma-bu-quan-bu-qu-fen-da-xiao-xie",
      "author": "javaLYG",
      "avatar": "https://www.liuyg.cn/icon.png"
    },
    {
      "title": "WAFPRO 防御加速 CDN 新版上线",
      "created": "2024-11-29 00:00",
      "link": "https://dusays.com/773/",
      "author": "杜老师说",
      "avatar": "https://cdn.qyliu.top/i/2024/08/04/66af33a4d6643.webp"
    },
    {
      "title": "用 Markdown 链接替换部分 Hexo 标签语法",
      "created": "2024-11-28 23:35",
      "link": "https://blog.uuanqin.top/p/fb28dce2/",
      "author": "半方池水",
      "avatar": "https://cdn.qyliu.top/i/2024/04/14/661bf5b9d3d5c.png"
    },
    {
      "title": "GM219-S光猫获取超管密码和宽带密码并改为桥接模式",
      "created": "2024-11-28 19:48",
      "link": "https://www.wxy97.com/archives/775f6cdd-da86-47ea-b4ee-3f9288b6f3df",
      "author": "人生若只如初见",
      "avatar": "https://cdn.wxy97.com/blog/2024-07-10-ormeeemh.webp"
    },
    {
      "title": "法律文书：刑事案件请求法院依法强制证人到庭作证的申请书",
      "created": "2024-11-28 18:33",
      "link": "https://xingbianren.cn/post/283.html",
      "author": "刑辩人在路上",
      "avatar": "https://xingbianren.cn/zb_users/upload/2023/05/202305231684818664504571.png"
    },
    {
      "title": "百度的AI助手真拉垮，简单的数字题都能计算错，看我如何纠正它",
      "created": "2024-11-28 17:38",
      "link": "https://simonsu.cn/p/1096/",
      "author": "SimonSu",
      "avatar": "https://simonsu.cn/static/images/qcode.png"
    },
    {
      "title": "该换什么牌子手机了？",
      "created": "2024-11-28 17:34",
      "link": "https://qq.mba/196.html",
      "author": "满心记",
      "avatar": "https://cdn.qyliu.top/i/2024/08/04/66af31bec75a0.webp"
    },
    {
      "title": "简单2步完成任务，免费领取通义灵码限量帆布包",
      "created": "2024-11-28 15:12",
      "link": "https://www.wangdu.site/fuliyouhui/2173.html",
      "author": "文武科技柜",
      "avatar": "https://www.wangdu.site/wp-content/uploads/2021/08/favicon.png"
    },
    {
      "title": "HelloGitHub 第 104 期",
      "created": "2024-11-28 08:15",
      "link": "https://hellogithub.com/periodical/volume/104",
      "author": "hellogithub",
      "avatar": "https://cravatar.cn/avatar/f2134513983f3f5225d92b2c07da758c?d=mp&s=80"
    },
    {
      "title": "自定义 Hexo 中的超链接样式",
      "created": "2024-11-27 23:35",
      "link": "https://blog.uuanqin.top/p/8aa53d93/",
      "author": "半方池水",
      "avatar": "https://cdn.qyliu.top/i/2024/04/14/661bf5b9d3d5c.png"
    },
    {
      "title": "Music Player for Windows and Android",
      "created": "2024-11-27 23:15",
      "link": "https://vluv.space/Tools/entertainment/music_player/",
      "author": "GnixAij",
      "avatar": "https://cdn.qyliu.top/i/2024/09/23/66f185d450ff3.webp"
    },
    {
      "title": "风记星辰的参考与设计：优化文章作者及版权区域、新增全局地图标注、渐进式背景模糊探索",
      "created": "2024-11-27 22:38",
      "link": "https://www.thyuu.com/79066",
      "author": "风记星辰",
      "avatar": "https://cdn.qyliu.top/i/2024/08/04/66af2d2430f68.webp"
    },
    {
      "title": "Canvas雪花动画",
      "created": "2024-11-27 17:06",
      "link": "https://www.aimiliy.top/posts/ba45cc7d.html",
      "author": "MuXiaoChen",
      "avatar": "https://cdn.qyliu.top/i/2024/09/20/66ed45792c171.webp"
    },
    {
      "title": "小陶的硕士毕业论文致谢",
      "created": "2024-11-27 11:45",
      "link": "https://www.52txr.cn/2024/GraduationThanks.html",
      "author": "陶小桃Blog",
      "avatar": "https://z1.ax1x.com/2023/01/12/pSuDn6H.png"
    },
    {
      "title": "低内存阿里云服务器搭建网站CPU、磁盘读取BPS异常问题解决方案",
      "created": "2024-11-27 11:01",
      "link": "https://blog.chengpei.top/archives/aliyun-ecs-exception-resolve",
      "author": "没事发个呆",
      "avatar": "https://chengpei.top/upload/WechatIMG70.jpg"
    },
    {
      "title": "Svg描边Loading动画",
      "created": "2024-11-27 10:49",
      "link": "https://www.hudi.space/posts/ca287c24/",
      "author": "短巷与雨",
      "avatar": "https://cdn.qyliu.top/i/2024/11/18/673ac90233753.webp"
    },
    {
      "title": "刘院长与张局长惺惺相惜，共同抵御官场逆淘汰",
      "created": "2024-11-27 09:07",
      "link": "https://xingbianren.cn/post/282.html",
      "author": "刑辩人在路上",
      "avatar": "https://xingbianren.cn/zb_users/upload/2023/05/202305231684818664504571.png"
    },
    {
      "title": "javascript学习01",
      "created": "2024-11-27 05:07",
      "link": "https://blog.ciraos.top/posts/javascript-study01",
      "author": "葱苓sama",
      "avatar": "https://cdn.qyliu.top/i/2024/05/03/663458df4e6f0.png"
    },
    {
      "title": "【第一感受】影像创作社区-王建章的摄影课",
      "created": "2024-11-26 21:05",
      "link": "https://hapgpt.com/archives/lKcY7Eoy",
      "author": "小莫分享",
      "avatar": "https://cravatar.cn/avatar/8f66161f3fd90add0e967cfa8843bc04?d=mp&s=80"
    },
    {
      "title": "创意工坊预览图被打码解决措施",
      "created": "2024-11-26 19:26",
      "link": "https://www.peterjxl.com/steam/workshop-mosaic/",
      "author": "从 01 开始",
      "avatar": "https://image.peterjxl.com/blog/re0.jpg"
    },
    {
      "title": "四时山水图册",
      "created": "2024-11-26 18:38",
      "link": "https://www.shuge.org/view/si_shi_shan_shui_tu_ce/",
      "author": "书格",
      "avatar": "https://www.shuge.org/wp-content/themes/artview/images/layout/logo.png"
    },
    {
      "title": "阿里云服务器搭建网站CPU、磁盘读取BPS异常问题排查记录",
      "created": "2024-11-26 15:33",
      "link": "https://blog.chengpei.top/archives/aliyun-ecs-exception",
      "author": "没事发个呆",
      "avatar": "https://chengpei.top/upload/WechatIMG70.jpg"
    },
    {
      "title": "我嘞个豆！原来 C/C++ 宏还可以这么玩啊？",
      "created": "2024-11-26 09:46",
      "link": "https://www.seayj.cn/articles/44d9e9a3/",
      "author": "SeaEpoch",
      "avatar": "https://cdn.qyliu.top/i/2024/11/10/672f8a9c7a5ba.webp"
    },
    {
      "title": "Baby shark 大战迅雷",
      "created": "2024-11-26 09:26",
      "link": "https://h4ck.org.cn/2024/11/18666",
      "author": "obaby",
      "avatar": "https://cdn.qyliu.top/i/2024/04/15/661d443b5359c.png"
    },
    {
      "title": "无畏云 CDN 加速免费依旧",
      "created": "2024-11-26 00:00",
      "link": "https://dusays.com/772/",
      "author": "杜老师说",
      "avatar": "https://cdn.qyliu.top/i/2024/08/04/66af33a4d6643.webp"
    },
    {
      "title": "创意工坊被锁国区解决措施",
      "created": "2024-11-25 19:26",
      "link": "https://www.peterjxl.com/steam/workshop/Lock-area/",
      "author": "从 01 开始",
      "avatar": "https://image.peterjxl.com/blog/re0.jpg"
    },
    {
      "title": "泛型编程相关理论学习",
      "created": "2024-11-25 15:41",
      "link": "https://vluv.space/Lang/Java/generic_theories/",
      "author": "GnixAij",
      "avatar": "https://cdn.qyliu.top/i/2024/09/23/66f185d450ff3.webp"
    },
    {
      "title": "有点智能，但不多",
      "created": "2024-11-25 15:12",
      "link": "https://lanxing.net/archives/226/",
      "author": "揽星",
      "avatar": "https://cdn.qyliu.top/i/2024/04/07/6612410571110.png"
    },
    {
      "title": "“不就是”与“又怎样”",
      "created": "2024-11-25 08:00",
      "link": "https://blog.xxfer.cn/posts/e8c4dc13.html",
      "author": "小李同学",
      "avatar": "https://cdn.qyliu.top/i/2024/11/28/6747439e8f0f9.webp"
    },
    {
      "title": "侧边栏——Solitude主题",
      "created": "2024-11-25 00:01",
      "link": "http://ymxblog.us.kg/posts/dca7dbdb.html",
      "author": "叶泯希",
      "avatar": "https://cdn.qyliu.top/i/2024/11/27/6747341ba9c31.webp"
    },
    {
      "title": "『月夜杂记241123期』寒风呼啸小雪临，银装素裹映晴霖",
      "created": "2024-11-24 23:55",
      "link": "https://www.iczrx.cn/archives/131/",
      "author": "晚夜",
      "avatar": "https://cdn.qyliu.top/i/2024/10/06/6702aa07d5bd8.webp"
    },
    {
      "title": "弹幕留言板——Solitude主题",
      "created": "2024-11-24 22:23",
      "link": "http://ymxblog.us.kg/posts/efc9bbdc.html",
      "author": "叶泯希",
      "avatar": "https://cdn.qyliu.top/i/2024/11/27/6747341ba9c31.webp"
    },
    {
      "title": "贾树森 大神教你成为手机摄影高手",
      "created": "2024-11-24 21:43",
      "link": "https://hapgpt.com/archives/e7k0T0UE",
      "author": "小莫分享",
      "avatar": "https://cravatar.cn/avatar/8f66161f3fd90add0e967cfa8843bc04?d=mp&s=80"
    },
    {
      "title": "光影魔方 商业PS后期课进阶班课程",
      "created": "2024-11-24 21:41",
      "link": "https://hapgpt.com/archives/CUGPSEkh",
      "author": "小莫分享",
      "avatar": "https://cravatar.cn/avatar/8f66161f3fd90add0e967cfa8843bc04?d=mp&s=80"
    },
    {
      "title": "剪映视频剪辑从小白到大师（电脑版）教程+PDF+配套素材",
      "created": "2024-11-24 21:40",
      "link": "https://hapgpt.com/archives/BmdmcPUt",
      "author": "小莫分享",
      "avatar": "https://cravatar.cn/avatar/8f66161f3fd90add0e967cfa8843bc04?d=mp&s=80"
    },
    {
      "title": "记一个有趣的C++报错：Run-Time Check Failure #2 - Stack around the variable &#039;p&#039; was corrupted",
      "created": "2024-11-24 21:07",
      "link": "https://www.52txr.cn/2024/RunTimeCheckFailure.html",
      "author": "陶小桃Blog",
      "avatar": "https://z1.ax1x.com/2023/01/12/pSuDn6H.png"
    },
    {
      "title": "行走人生",
      "created": "2024-11-24 18:52",
      "link": "https://maie.name/1012.html",
      "author": "流浪天下",
      "avatar": "https://img.maie.name/2016/04/cropped-favicon-32x32.png"
    },
    {
      "title": "在线人数统计和动态图片教程",
      "created": "2024-11-24 09:59",
      "link": "https://vjo.cc/1554",
      "author": "刘郎阁",
      "avatar": "https://cdn.qyliu.top/i/2024/04/19/66229406a68df.png"
    },
    {
      "title": "Ephemeralis-Weekly（13）：生活的起伏",
      "created": "2024-11-24 08:00",
      "link": "https://www.yoghurtlee.com/weekly-13/",
      "author": "Chlorine",
      "avatar": "https://cdn.qyliu.top/i/2024/08/07/66b2daf9ab79f.webp"
    },
    {
      "title": "Python项目生成依赖文件",
      "created": "2024-11-24 05:36",
      "link": "https://blog.randench.cn/posts/43649/",
      "author": "RE Blog",
      "avatar": "https://cdn.qyliu.top/i/2024/11/19/673cb26cbdb2e.webp"
    },
    {
      "title": "分享十八款知名的远程控制工具",
      "created": "2024-11-24 04:00",
      "link": "https://www.peterjxl.com/Remote-control/recommend/",
      "author": "从 01 开始",
      "avatar": "https://image.peterjxl.com/blog/re0.jpg"
    },
    {
      "title": "腹肌养成记",
      "created": "2024-11-23 18:00",
      "link": "https://h.liyy.us.kg/2024/11/23/fjyangcheng/",
      "author": "茗辰原",
      "avatar": "https://cdn.qyliu.top/i/2024/04/21/66249e0a775f8.png"
    },
    {
      "title": "WeekNote 2024-47",
      "created": "2024-11-23 16:44",
      "link": "https://hp-l.github.io/2024/11/23/164452/",
      "author": "子书承宇",
      "avatar": "https://cdn.qyliu.top/i/2024/11/11/67321d6dcee8e.webp"
    },
    {
      "title": "Office-2025激活",
      "created": "2024-11-23 10:00",
      "link": "https://h.liyy.us.kg/2024/11/23/office-ltsc/",
      "author": "茗辰原",
      "avatar": "https://cdn.qyliu.top/i/2024/04/21/66249e0a775f8.png"
    },
    {
      "title": "将不蒜子中的数据迁移到 Waline",
      "created": "2024-11-23 02:55",
      "link": "https://blog.uuanqin.top/p/e400f664/",
      "author": "半方池水",
      "avatar": "https://cdn.qyliu.top/i/2024/04/14/661bf5b9d3d5c.png"
    },
    {
      "title": "溶液中离子浓度大小比较-第一讲",
      "created": "2024-11-23 00:01",
      "link": "https://www.iczrx.cn/archives/130/",
      "author": "晚夜",
      "avatar": "https://cdn.qyliu.top/i/2024/10/06/6702aa07d5bd8.webp"
    },
    {
      "title": "新版本不蒜子统计平台使用说明",
      "created": "2024-11-23 00:00",
      "link": "https://dusays.com/771/",
      "author": "杜老师说",
      "avatar": "https://cdn.qyliu.top/i/2024/08/04/66af33a4d6643.webp"
    },
    {
      "title": "语言是一个人真正的祖国",
      "created": "2024-11-22 21:16",
      "link": "https://xingbianren.cn/post/281.html",
      "author": "刑辩人在路上",
      "avatar": "https://xingbianren.cn/zb_users/upload/2023/05/202305231684818664504571.png"
    },
    {
      "title": "Mix-Space后端Core使用远程数据库",
      "created": "2024-11-22 21:09",
      "link": "https://www.vlo.cc/posts/jc/MixSpace_backend_Core_uses_remote_database",
      "author": "华岁云小屋",
      "avatar": "https://mx.vlo.cc/api/v2/objects/avatar/t3vpbdbvpmo0o3eduy.jpg"
    },
    {
      "title": "解决微软商店软件崩溃（0x80073CFA与0x80073CF9）",
      "created": "2024-11-22 19:32",
      "link": "https://www.seayj.cn/articles/89987d18/",
      "author": "SeaEpoch",
      "avatar": "https://cdn.qyliu.top/i/2024/11/10/672f8a9c7a5ba.webp"
    },
    {
      "title": "Docker Compose启动提示: compose.yml: the attribute `version` is obsolete",
      "created": "2024-11-22 16:10",
      "link": "https://www.wxy97.com/archives/567e1697-985b-4dc7-b922-730f5acf1664",
      "author": "人生若只如初见",
      "avatar": "https://cdn.wxy97.com/blog/2024-07-10-ormeeemh.webp"
    },
    {
      "title": "自建不蒜子API",
      "created": "2024-11-22 15:32",
      "link": "https://www.aimiliy.top/posts/17f43b12.html",
      "author": "MuXiaoChen",
      "avatar": "https://cdn.qyliu.top/i/2024/09/20/66ed45792c171.webp"
    },
    {
      "title": "独立博客自省问卷15题",
      "created": "2024-11-22 15:11",
      "link": "https://lanxing.net/archives/225/",
      "author": "揽星",
      "avatar": "https://cdn.qyliu.top/i/2024/04/07/6612410571110.png"
    },
    {
      "title": "无畏云跑路了？",
      "created": "2024-11-22 08:49",
      "link": "https://qq.mba/195.html",
      "author": "满心记",
      "avatar": "https://cdn.qyliu.top/i/2024/08/04/66af31bec75a0.webp"
    },
    {
      "title": "科技爱好者周刊（第 326 期）：世界没有那么多财富",
      "created": "2024-11-22 08:00",
      "link": "http://www.ruanyifeng.com/blog/2024/11/weekly-issue-326.html",
      "author": "阮一峰的网络日志",
      "avatar": "https://www.ruanyifeng.com/blog/images/person2_s.jpg"
    },
    {
      "title": "太子城 O 型穿越之一向导家到水依海子营地",
      "created": "2024-11-21 23:27",
      "link": "https://maie.name/853.html",
      "author": "流浪天下",
      "avatar": "https://img.maie.name/2016/04/cropped-favicon-32x32.png"
    },
    {
      "title": "藕香零拾",
      "created": "2024-11-21 17:21",
      "link": "https://www.shuge.org/view/ou_xiang_ling_shi/",
      "author": "书格",
      "avatar": "https://www.shuge.org/wp-content/themes/artview/images/layout/logo.png"
    },
    {
      "title": "基于Apache POI随机生成儿子的合成分解算术题",
      "created": "2024-11-21 15:30",
      "link": "https://blog.chengpei.top/archives/ji-yu-poi-timu",
      "author": "没事发个呆",
      "avatar": "https://chengpei.top/upload/WechatIMG70.jpg"
    },
    {
      "title": "翻译谁家强？一句：Made on Earth by humans 就看出来了",
      "created": "2024-11-20 21:52",
      "link": "https://simonsu.cn/p/994/",
      "author": "SimonSu",
      "avatar": "https://simonsu.cn/static/images/qcode.png"
    },
    {
      "title": "网易云音乐脚本",
      "created": "2024-11-20 18:00",
      "link": "https://h.liyy.us.kg/2024/11/20/wyy--2/",
      "author": "茗辰原",
      "avatar": "https://cdn.qyliu.top/i/2024/04/21/66249e0a775f8.png"
    },
    {
      "title": "frp安装和使用并结合nginx配置域名https访问",
      "created": "2024-11-20 16:08",
      "link": "https://www.wxy97.com/archives/284c90ae-c88e-4928-b024-85380e995e06",
      "author": "人生若只如初见",
      "avatar": "https://cdn.wxy97.com/blog/2024-07-10-ormeeemh.webp"
    },
    {
      "title": "自建Docker镜像加速服务",
      "created": "2024-11-20 11:57",
      "link": "https://www.wxy97.com/archives/5ac59d19-da30-4cc8-a36e-9fe93a65b647",
      "author": "人生若只如初见",
      "avatar": "https://cdn.wxy97.com/blog/2024-07-10-ormeeemh.webp"
    },
    {
      "title": "开启 OpenResty 的 QUIC 支持",
      "created": "2024-11-20 00:00",
      "link": "https://dusays.com/770/",
      "author": "杜老师说",
      "avatar": "https://cdn.qyliu.top/i/2024/08/04/66af33a4d6643.webp"
    },
    {
      "title": "全面详细的常用Linux命令汇总（2）",
      "created": "2024-11-19 20:40",
      "link": "https://talen.top/posts/428fcd7a/",
      "author": "M.Talen",
      "avatar": "https://cdn.qyliu.top/i/2024/05/23/664eda97bdec6.png"
    },
    {
      "title": "零基础 WordPress 网站建设全攻略：域名注册、环境搭建及内容创作（2024.11）",
      "created": "2024-11-19 19:55",
      "link": "https://www.shephe.com/tutorial/wordpress-website-building/",
      "author": "Kevin's Space",
      "avatar": "https://cravatar.cn/avatar/cbbe656c7bb46772f589c9b18a7c747e?s=160&d=robohash&r=g%202x"
    },
    {
      "title": "秋水共长天",
      "created": "2024-11-19 08:00",
      "link": "https://blog.xxfer.cn/posts/19a02a21.html",
      "author": "小李同学",
      "avatar": "https://cdn.qyliu.top/i/2024/11/28/6747439e8f0f9.webp"
    },
    {
      "title": "Nginx配置端口重定向及协议重定向",
      "created": "2024-11-18 16:23",
      "link": "https://blog.chengpei.top/archives/nginx-rewrite",
      "author": "没事发个呆",
      "avatar": "https://chengpei.top/upload/WechatIMG70.jpg"
    },
    {
      "title": "C++ 中关闭 cin\\cout 同步及其利弊",
      "created": "2024-11-18 12:22",
      "link": "https://www.seayj.cn/articles/360b7110/",
      "author": "SeaEpoch",
      "avatar": "https://cdn.qyliu.top/i/2024/11/10/672f8a9c7a5ba.webp"
    },
    {
      "title": "近来杂记",
      "created": "2024-11-17 13:34",
      "link": "https://qq.mba/194.html",
      "author": "满心记",
      "avatar": "https://cdn.qyliu.top/i/2024/08/04/66af31bec75a0.webp"
    },
    {
      "title": "给侧边栏添加倒计时",
      "created": "2024-11-17 05:57",
      "link": "https://blog.randench.cn/posts/37015/",
      "author": "RE Blog",
      "avatar": "https://cdn.qyliu.top/i/2024/11/19/673cb26cbdb2e.webp"
    },
    {
      "title": "宝塔面板切换www目录位置",
      "created": "2024-11-17 00:50",
      "link": "https://blog.randench.cn/posts/29231/",
      "author": "RE Blog",
      "avatar": "https://cdn.qyliu.top/i/2024/11/19/673cb26cbdb2e.webp"
    },
    {
      "title": "在文章中添加条件勾选表单",
      "created": "2024-11-17 00:43",
      "link": "https://blog.randench.cn/posts/22407/",
      "author": "RE Blog",
      "avatar": "https://cdn.qyliu.top/i/2024/11/19/673cb26cbdb2e.webp"
    },
    {
      "title": "域名变更与馅饼的诱惑",
      "created": "2024-11-16 19:44",
      "link": "https://vjo.cc/1549",
      "author": "刘郎阁",
      "avatar": "https://cdn.qyliu.top/i/2024/04/19/66229406a68df.png"
    },
    {
      "title": "Hexo教程(二) 基本文件结构",
      "created": "2024-11-15 21:11",
      "link": "https://blog.elykia.cn/posts/19.html",
      "author": "Elykia",
      "avatar": "https://cdn.qyliu.top/i/2024/10/13/670b53452abec.webp"
    },
    {
      "title": "Windows 11 Start Menu Widgets(Phone Link)",
      "created": "2024-11-15 17:50",
      "link": "https://vluv.space/MISC/windows_companion/",
      "author": "GnixAij",
      "avatar": "https://cdn.qyliu.top/i/2024/09/23/66f185d450ff3.webp"
    },
    {
      "title": "【国内现货】One Nz：无月租无需实名超低费率的eSim新西兰电话卡",
      "created": "2024-11-15 17:15",
      "link": "https://www.wangdu.site/fuliyouhui/2171.html",
      "author": "文武科技柜",
      "avatar": "https://www.wangdu.site/wp-content/uploads/2021/08/favicon.png"
    },
    {
      "title": "显示器检测应从哪些方面入手，有哪些检测点？",
      "created": "2024-11-15 11:43",
      "link": "https://www.shephe.com/post/%e5%9c%a8%e7%ba%bf%e6%98%be%e7%a4%ba%e5%99%a8%e6%a3%80%e6%b5%8b/",
      "author": "Kevin's Space",
      "avatar": "https://cravatar.cn/avatar/cbbe656c7bb46772f589c9b18a7c747e?s=160&d=robohash&r=g%202x"
    },
    {
      "title": "科技爱好者周刊（第 325 期）：VS Code 编辑器的下一站是 Zed？",
      "created": "2024-11-15 08:05",
      "link": "http://www.ruanyifeng.com/blog/2024/11/weekly-issue-325.html",
      "author": "阮一峰的网络日志",
      "avatar": "https://www.ruanyifeng.com/blog/images/person2_s.jpg"
    },
    {
      "title": "做一个开心的牛马",
      "created": "2024-11-14 19:55",
      "link": "https://vjo.cc/1538",
      "author": "刘郎阁",
      "avatar": "https://cdn.qyliu.top/i/2024/04/19/66229406a68df.png"
    },
    {
      "title": "WebStrom/Idea 显示Error: No 'dev' npm script",
      "created": "2024-11-14 17:14",
      "link": "https://www.wxy97.com/archives/6d2ecb12-93e3-4963-9f6e-bc8d4bf6ef6a",
      "author": "人生若只如初见",
      "avatar": "https://cdn.wxy97.com/blog/2024-07-10-ormeeemh.webp"
    },
    {
      "title": "2024年推荐7款免费好用的国内外服务器传输工具",
      "created": "2024-11-14 16:08",
      "link": "https://www.wangdu.site/software/bianchengkaifa/2170.html",
      "author": "文武科技柜",
      "avatar": "https://www.wangdu.site/wp-content/uploads/2021/08/favicon.png"
    },
    {
      "title": "多1Panel面板域名SSL证书同步",
      "created": "2024-11-13 15:01",
      "link": "https://www.vlo.cc/posts/jc/1panel_sync_ssl",
      "author": "华岁云小屋",
      "avatar": "https://mx.vlo.cc/api/v2/objects/avatar/t3vpbdbvpmo0o3eduy.jpg"
    },
    {
      "title": "【知行小酒馆】对话张云帆——规划人生",
      "created": "2024-11-13 08:00",
      "link": "https://blog.xing-ye.top/posts/e0cc44a/",
      "author": "XINGYE",
      "avatar": "https://cdn.qyliu.top/i/2024/05/18/6648b84c682e1.png"
    },
    {
      "title": "[AcWing]区间合并",
      "created": "2024-11-12 17:42",
      "link": "https://www.seayj.cn/articles/adc75522/",
      "author": "SeaEpoch",
      "avatar": "https://cdn.qyliu.top/i/2024/11/10/672f8a9c7a5ba.webp"
    },
    {
      "title": "绿联 NAS DXP2800 试用手记",
      "created": "2024-11-12 16:31",
      "link": "https://maie.name/1009.html",
      "author": "流浪天下",
      "avatar": "https://img.maie.name/2016/04/cropped-favicon-32x32.png"
    },
    {
      "title": "51单片机使用NRF24L01进行2.4G无线通信",
      "created": "2024-11-12 14:10",
      "link": "https://blog.chengpei.top/archives/51-nrf24l01",
      "author": "没事发个呆",
      "avatar": "https://chengpei.top/upload/WechatIMG70.jpg"
    },
    {
      "title": "07-剧终：故事的开端与终末",
      "created": "2024-11-10 16:07",
      "link": "http://blog.awaae001.top/posts/11645.html",
      "author": "呓语梦轩",
      "avatar": "https://cdn.qyliu.top/i/2024/03/30/660769346d538.jpg"
    },
    {
      "title": "Ephemeralis-Weekly（12）：浮沫之下",
      "created": "2024-11-10 08:00",
      "link": "https://www.yoghurtlee.com/weekly-12/",
      "author": "Chlorine",
      "avatar": "https://cdn.qyliu.top/i/2024/08/07/66b2daf9ab79f.webp"
    },
    {
      "title": "24年十月上旬周记",
      "created": "2024-11-10 03:00",
      "link": "https://koxiuqiu.cn/2024/11y9d1/",
      "author": "朽丘博",
      "avatar": "https://cdn.qyliu.top/i/2024/08/20/66c41c9c45e2a.webp"
    },
    {
      "title": "[AcWing]位运算(二进制的最后一个 1)",
      "created": "2024-11-09 22:15",
      "link": "https://www.seayj.cn/articles/9f470bbc/",
      "author": "SeaEpoch",
      "avatar": "https://cdn.qyliu.top/i/2024/11/10/672f8a9c7a5ba.webp"
    },
    {
      "title": "开源 macOS 系统监视器，监控电脑各个参数",
      "created": "2024-11-09 17:44",
      "link": "https://xiangming.site/891.html",
      "author": "湘铭",
      "avatar": "https://cdn.qyliu.top/i/2024/04/19/6622928fc416c.png"
    },
    {
      "title": "到货了，第一台mac到手",
      "created": "2024-11-08 21:55",
      "link": "https://xiangming.site/888.html",
      "author": "湘铭",
      "avatar": "https://cdn.qyliu.top/i/2024/04/19/6622928fc416c.png"
    },
    {
      "title": "拒绝花里胡哨，返璞归真😶",
      "created": "2024-11-08 16:00",
      "link": "https://blog.xxfer.cn/posts/5a9ae0a2.html",
      "author": "小李同学",
      "avatar": "https://cdn.qyliu.top/i/2024/11/28/6747439e8f0f9.webp"
    },
    {
      "title": "借icefox改造了一个“朋友圈”",
      "created": "2024-11-08 14:43",
      "link": "https://qq.mba/192.html",
      "author": "满心记",
      "avatar": "https://cdn.qyliu.top/i/2024/08/04/66af31bec75a0.webp"
    },
    {
      "title": "云部署Hexo和Certbot申请",
      "created": "2024-11-07 19:20",
      "link": "https://www.hudi.space/posts/b632734/",
      "author": "短巷与雨",
      "avatar": "https://cdn.qyliu.top/i/2024/11/18/673ac90233753.webp"
    },
    {
      "title": "立冬",
      "created": "2024-11-07 15:09",
      "link": "https://lanxing.net/archives/224/",
      "author": "揽星",
      "avatar": "https://cdn.qyliu.top/i/2024/04/07/6612410571110.png"
    },
    {
      "title": "风记星辰冬季壹言：朔风寒将至·冬日暖人心",
      "created": "2024-11-07 09:17",
      "link": "https://www.thyuu.com/78931",
      "author": "风记星辰",
      "avatar": "https://cdn.qyliu.top/i/2024/08/04/66af2d2430f68.webp"
    },
    {
      "title": "Hexo教程(一) 博客更新指南",
      "created": "2024-11-06 21:47",
      "link": "https://blog.elykia.cn/posts/18.html",
      "author": "Elykia",
      "avatar": "https://cdn.qyliu.top/i/2024/10/13/670b53452abec.webp"
    },
    {
      "title": "Python Dev Log.1",
      "created": "2024-11-06 21:02",
      "link": "https://vluv.space/Lang/Python/pydevlog1/",
      "author": "GnixAij",
      "avatar": "https://cdn.qyliu.top/i/2024/09/23/66f185d450ff3.webp"
    },
    {
      "title": "日常加班、Alist优化和WiFi密码",
      "created": "2024-11-06 10:22",
      "link": "https://vjo.cc/1528",
      "author": "刘郎阁",
      "avatar": "https://cdn.qyliu.top/i/2024/04/19/66229406a68df.png"
    },
    {
      "title": "”挑战杯“了解",
      "created": "2024-11-06 09:07",
      "link": "http://xlwlgzs.com/archives/tzbxm",
      "author": "小陆yaの博客",
      "avatar": "https://cdn.qyliu.top/i/2024/08/18/66c1b740ad40d.webp"
    },
    {
      "title": "【持续更新...】Docker封禁：国内可用docker镜像源",
      "created": "2024-11-04 02:00",
      "link": "https://blog.xxfer.cn/posts/308a1d42.html",
      "author": "小李同学",
      "avatar": "https://cdn.qyliu.top/i/2024/11/28/6747439e8f0f9.webp"
    },
    {
      "title": "VitePress 不完全优化指南",
      "created": "2024-11-03 17:54",
      "link": "https://blog.zhilu.cyou/2024/vitepress-enhancement",
      "author": "纸鹿本鹿",
      "avatar": "https://cdn.qyliu.top/i/2024/06/02/665c869ded7cd.png"
    },
    {
      "title": "EasyPub-轻量Kindle电子书格式转换工具",
      "created": "2024-11-03 14:47",
      "link": "http://blog.awaae001.top/posts/859850.html",
      "author": "呓语梦轩",
      "avatar": "https://cdn.qyliu.top/i/2024/03/30/660769346d538.jpg"
    },
    {
      "title": "威联通 使用Docker快速部署CertD并自动申请免费泛域名SSL证书",
      "created": "2024-11-02 13:59",
      "link": "https://xiangming.site/881.html",
      "author": "湘铭",
      "avatar": "https://cdn.qyliu.top/i/2024/04/19/6622928fc416c.png"
    },
    {
      "title": "数字电路设计与嵌入式开发——组合逻辑电路的Verilog实现",
      "created": "2024-11-01 14:51",
      "link": "https://vluv.space/UESTC/FPGA/lab2/",
      "author": "GnixAij",
      "avatar": "https://cdn.qyliu.top/i/2024/09/23/66f185d450ff3.webp"
    },
    {
      "title": "月度随笔|2024-10",
      "created": "2024-11-01 08:00",
      "link": "https://blog.xing-ye.top/posts/9cc0e153/",
      "author": "XINGYE",
      "avatar": "https://cdn.qyliu.top/i/2024/05/18/6648b84c682e1.png"
    },
    {
      "title": "Follow体验",
      "created": "2024-10-30 09:24",
      "link": "https://lanxing.net/archives/223/",
      "author": "揽星",
      "avatar": "https://cdn.qyliu.top/i/2024/04/07/6612410571110.png"
    },
    {
      "title": "Farewell，Omnivore",
      "created": "2024-10-30 08:00",
      "link": "https://www.yoghurtlee.com/farewell-omnivore/",
      "author": "Chlorine",
      "avatar": "https://cdn.qyliu.top/i/2024/08/07/66b2daf9ab79f.webp"
    },
    {
      "title": "【日常分享】页面美化",
      "created": "2024-10-30 01:09",
      "link": "https://www.aimiliy.top/posts/3275e913.html",
      "author": "MuXiaoChen",
      "avatar": "https://cdn.qyliu.top/i/2024/09/20/66ed45792c171.webp"
    },
    {
      "title": "风记得的第1612天星辰：错把剧情混现实，一时难分与谁离 —— 电影《毒液》系列感情向影评",
      "created": "2024-10-29 17:22",
      "link": "https://www.thyuu.com/78802",
      "author": "风记星辰",
      "avatar": "https://cdn.qyliu.top/i/2024/08/04/66af2d2430f68.webp"
    },
    {
      "title": "Follow：信息浏览聚合，万物皆可订阅",
      "created": "2024-10-29 14:51",
      "link": "https://talen.top/posts/12bfa1c7/",
      "author": "M.Talen",
      "avatar": "https://cdn.qyliu.top/i/2024/05/23/664eda97bdec6.png"
    },
    {
      "title": "Flume基础学习",
      "created": "2024-10-28 12:28",
      "link": "https://www.hudi.space/posts/1e46a8be/",
      "author": "短巷与雨",
      "avatar": "https://cdn.qyliu.top/i/2024/11/18/673ac90233753.webp"
    },
    {
      "title": "给电脑新手的笔记本开荒指南导读",
      "created": "2024-10-28 08:23",
      "link": "https://blog.zhilu.cyou/2024/new-laptop-guide",
      "author": "纸鹿本鹿",
      "avatar": "https://cdn.qyliu.top/i/2024/06/02/665c869ded7cd.png"
    },
    {
      "title": "HelloGitHub 第 103 期",
      "created": "2024-10-28 08:04",
      "link": "https://hellogithub.com/periodical/volume/103",
      "author": "hellogithub",
      "avatar": "https://cravatar.cn/avatar/f2134513983f3f5225d92b2c07da758c?d=mp&s=80"
    },
    {
      "title": "知乎图片去水印下载的方法",
      "created": "2024-10-27 23:22",
      "link": "https://blog.elykia.cn/posts/17.html",
      "author": "Elykia",
      "avatar": "https://cdn.qyliu.top/i/2024/10/13/670b53452abec.webp"
    },
    {
      "title": "Ephemeralis-Weekly（11）：案几之上",
      "created": "2024-10-27 08:00",
      "link": "https://www.yoghurtlee.com/weekly-11/",
      "author": "Chlorine",
      "avatar": "https://cdn.qyliu.top/i/2024/08/07/66b2daf9ab79f.webp"
    },
    {
      "title": "周六吐槽",
      "created": "2024-10-26 15:51",
      "link": "https://xiangming.site/875.html",
      "author": "湘铭",
      "avatar": "https://cdn.qyliu.top/i/2024/04/19/6622928fc416c.png"
    },
    {
      "title": "域名 DNS 服务托管至 Cloudflare 以及 301 重定向的配置",
      "created": "2024-10-26 03:32",
      "link": "https://blog.uuanqin.top/p/41b77d61/",
      "author": "半方池水",
      "avatar": "https://cdn.qyliu.top/i/2024/04/14/661bf5b9d3d5c.png"
    },
    {
      "title": "24年10月小结",
      "created": "2024-10-25 23:00",
      "link": "https://koxiuqiu.cn/2024/10y25d1/",
      "author": "朽丘博",
      "avatar": "https://cdn.qyliu.top/i/2024/08/20/66c41c9c45e2a.webp"
    },
    {
      "title": "安知鱼主题文件魔改记录",
      "created": "2024-10-25 00:34",
      "link": "https://blog.elykia.cn/posts/16.html",
      "author": "Elykia",
      "avatar": "https://cdn.qyliu.top/i/2024/10/13/670b53452abec.webp"
    },
    {
      "title": "QRcodeGen项目介绍，基于Python打造二维码生成新利器",
      "created": "2024-10-23 21:49",
      "link": "https://talen.top/posts/5788ce36/",
      "author": "M.Talen",
      "avatar": "https://cdn.qyliu.top/i/2024/05/23/664eda97bdec6.png"
    },
    {
      "title": "Oracle学习基础",
      "created": "2024-10-23 16:12",
      "link": "https://www.hudi.space/posts/7b34242e/",
      "author": "短巷与雨",
      "avatar": "https://cdn.qyliu.top/i/2024/11/18/673ac90233753.webp"
    },
    {
      "title": "Picgo+Typora+SMMS图床配置",
      "created": "2024-10-23 13:36",
      "link": "https://www.hudi.space/posts/532806c/",
      "author": "短巷与雨",
      "avatar": "https://cdn.qyliu.top/i/2024/11/18/673ac90233753.webp"
    },
    {
      "title": "【关于】、【音乐盒】页面美化记录",
      "created": "2024-10-21 10:27",
      "link": "https://www.aimiliy.top/posts/5c19c6c5.html",
      "author": "MuXiaoChen",
      "avatar": "https://cdn.qyliu.top/i/2024/09/20/66ed45792c171.webp"
    },
    {
      "title": "vscode配置C/C++运行环境",
      "created": "2024-10-20 02:08",
      "link": "https://blog.ciraos.top/posts/vscode-CPP-Runtime",
      "author": "葱苓sama",
      "avatar": "https://cdn.qyliu.top/i/2024/05/03/663458df4e6f0.png"
    },
    {
      "title": "再谈考试时钟：技术之外的思考",
      "created": "2024-10-18 16:50",
      "link": "https://blog.zhilu.cyou/2024/exam-clock-thinking",
      "author": "纸鹿本鹿",
      "avatar": "https://cdn.qyliu.top/i/2024/06/02/665c869ded7cd.png"
    },
    {
      "title": "本站更新公告-20241016",
      "created": "2024-10-16 01:16",
      "link": "https://www.zouht.com/3818.html",
      "author": "ChrisKim",
      "avatar": "https://cdn.qyliu.top/i/2024/06/27/667d880789765.webp"
    },
    {
      "title": "济南 & 泰山游记！",
      "created": "2024-10-15 20:12",
      "link": "https://www.zouht.com/3800.html",
      "author": "ChrisKim",
      "avatar": "https://cdn.qyliu.top/i/2024/06/27/667d880789765.webp"
    },
    {
      "title": "自制/手搓麦克森八木天线记录",
      "created": "2024-10-13 08:00",
      "link": "https://cworld0.com/blog/yagi",
      "author": "CWorld",
      "avatar": "https://cdn.qyliu.top/i/2024/11/18/673b5d44a04dd.webp"
    },
    {
      "title": "废话校园日常",
      "created": "2024-10-13 06:00",
      "link": "https://koxiuqiu.cn/2024/10y12d1/",
      "author": "朽丘博",
      "avatar": "https://cdn.qyliu.top/i/2024/08/20/66c41c9c45e2a.webp"
    },
    {
      "title": "【转载】有关「青春感」",
      "created": "2024-10-12 17:18",
      "link": "https://www.himiku.com/archives/about-youthful-feeling.html",
      "author": "初之音",
      "avatar": "https://cravatar.cn/avatar/2fc4cf3560ff5a1cc64ea029896ab235?s=400"
    },
    {
      "title": "Nginx 可视化编辑工具 Nginx UI 安装和使用",
      "created": "2024-10-10 13:31",
      "link": "https://talen.top/posts/6c9e1bd7/",
      "author": "M.Talen",
      "avatar": "https://cdn.qyliu.top/i/2024/05/23/664eda97bdec6.png"
    },
    {
      "title": "今日校园见闻：我已经出离高兴了",
      "created": "2024-10-09 22:32",
      "link": "https://blog.zhilu.cyou/2024/observe-at-school",
      "author": "纸鹿本鹿",
      "avatar": "https://cdn.qyliu.top/i/2024/06/02/665c869ded7cd.png"
    },
    {
      "title": "游玩《黑神话：悟空》的一些想法",
      "created": "2024-10-08 16:18",
      "link": "https://www.zouht.com/3790.html",
      "author": "ChrisKim",
      "avatar": "https://cdn.qyliu.top/i/2024/06/27/667d880789765.webp"
    },
    {
      "title": "业余无线电进阶玩法",
      "created": "2024-10-07 08:00",
      "link": "https://cworld0.com/blog/amateur-radio-2",
      "author": "CWorld",
      "avatar": "https://cdn.qyliu.top/i/2024/11/18/673b5d44a04dd.webp"
    },
    {
      "title": "ANI-RSS：自动追番新姿势！",
      "created": "2024-10-07 00:13",
      "link": "https://www.himiku.com/archives/ani-rss.html",
      "author": "初之音",
      "avatar": "https://cravatar.cn/avatar/2fc4cf3560ff5a1cc64ea029896ab235?s=400"
    },
    {
      "title": "泉盛 UV-K6 上手指南",
      "created": "2024-10-06 08:00",
      "link": "https://cworld0.com/blog/uv-k6",
      "author": "CWorld",
      "avatar": "https://cdn.qyliu.top/i/2024/11/18/673b5d44a04dd.webp"
    },
    {
      "title": "LEDCDN小说明",
      "created": "2024-10-04 04:00",
      "link": "https://koxiuqiu.cn/2024/ledcdn/",
      "author": "朽丘博",
      "avatar": "https://cdn.qyliu.top/i/2024/08/20/66c41c9c45e2a.webp"
    },
    {
      "title": "九月音乐记录",
      "created": "2024-10-03 09:15",
      "link": "https://www.vlo.cc/notes/16",
      "author": "华岁云小屋",
      "avatar": "https://mx.vlo.cc/api/v2/objects/avatar/t3vpbdbvpmo0o3eduy.jpg"
    },
    {
      "title": "【开源软件】HivisionIDPhoto：一个轻量级的AI证件照在线制作工具",
      "created": "2024-10-01 00:21",
      "link": "https://gyhwd.top/archives/18ZGEjBp",
      "author": "青竹小轩",
      "avatar": "https://cdn.qyliu.top/i/2024/04/23/662748990165a.png"
    },
    {
      "title": "Follow邀请码",
      "created": "2024-09-28 10:14",
      "link": "https://www.vlo.cc/notes/15",
      "author": "华岁云小屋",
      "avatar": "https://mx.vlo.cc/api/v2/objects/avatar/t3vpbdbvpmo0o3eduy.jpg"
    },
    {
      "title": "HelloGitHub 第 102 期",
      "created": "2024-09-27 07:55",
      "link": "https://hellogithub.com/periodical/volume/102",
      "author": "hellogithub",
      "avatar": "https://cravatar.cn/avatar/f2134513983f3f5225d92b2c07da758c?d=mp&s=80"
    },
    {
      "title": "月度随笔|2024-08&09",
      "created": "2024-09-22 08:00",
      "link": "https://blog.xing-ye.top/posts/9edcc8c/",
      "author": "XINGYE",
      "avatar": "https://cdn.qyliu.top/i/2024/05/18/6648b84c682e1.png"
    },
    {
      "title": "Zotero与Word：轻松添加引用超链接的技巧",
      "created": "2024-09-21 13:21",
      "link": "https://gyhwd.top/archives/yYQQalx4",
      "author": "青竹小轩",
      "avatar": "https://cdn.qyliu.top/i/2024/04/23/662748990165a.png"
    },
    {
      "title": "Nextjs笔记",
      "created": "2024-09-17 21:36",
      "link": "https://blog.ciraos.top/posts/NextjsNote",
      "author": "葱苓sama",
      "avatar": "https://cdn.qyliu.top/i/2024/05/03/663458df4e6f0.png"
    },
    {
      "title": "【破事水】-对于未来的前瞻于回望",
      "created": "2024-09-17 15:26",
      "link": "http://blog.awaae001.top/posts/39440.html",
      "author": "呓语梦轩",
      "avatar": "https://cdn.qyliu.top/i/2024/03/30/660769346d538.jpg"
    },
    {
      "title": "设计网站,设计生你能用到的站点-欢迎收藏~",
      "created": "2024-09-16 07:15",
      "link": "http://xlwlgzs.com/archives/sjswz",
      "author": "小陆yaの博客",
      "avatar": "https://cdn.qyliu.top/i/2024/08/18/66c1b740ad40d.webp"
    },
    {
      "title": "你好，世界！",
      "created": "2024-09-15 02:00",
      "link": "https://blog.ciraos.top/posts/helloworld",
      "author": "葱苓sama",
      "avatar": "https://cdn.qyliu.top/i/2024/05/03/663458df4e6f0.png"
    },
    {
      "title": "阴阳师八周年活动-非酋的自我修养记录",
      "created": "2024-09-12 16:30",
      "link": "https://www.gan1ser.top/post/4bfe597f.html",
      "author": "GanSer",
      "avatar": "https://cdn.qyliu.top/i/2024/04/29/662fbba91addc.png"
    },
    {
      "title": "如何快速找到你的 Windows 激活密钥和 OEM 数字许可证",
      "created": "2024-09-04 11:27",
      "link": "https://gyhwd.top/archives/gi3T0IeQ",
      "author": "青竹小轩",
      "avatar": "https://cdn.qyliu.top/i/2024/04/23/662748990165a.png"
    },
    {
      "title": "Windows工具-让你的Windows锦上添花，添了又添",
      "created": "2024-09-01 11:24",
      "link": "http://blog.awaae001.top/posts/44173.html",
      "author": "呓语梦轩",
      "avatar": "https://cdn.qyliu.top/i/2024/03/30/660769346d538.jpg"
    },
    {
      "title": "HelloGitHub 第 101 期",
      "created": "2024-08-28 08:03",
      "link": "https://hellogithub.com/periodical/volume/101",
      "author": "hellogithub",
      "avatar": "https://cravatar.cn/avatar/f2134513983f3f5225d92b2c07da758c?d=mp&s=80"
    },
    {
      "title": "🚀免费大学专属职业生涯规划模板来啦！",
      "created": "2024-08-20 15:57",
      "link": "http://xlwlgzs.com/archives/mian-fei-da-xue-zhuan-shu-zhi-ye-sheng-ya-gui-hua-mo-ban-lai-la",
      "author": "小陆yaの博客",
      "avatar": "https://cdn.qyliu.top/i/2024/08/18/66c1b740ad40d.webp"
    },
    {
      "title": "免费大学必备计算机二级资料来啦~",
      "created": "2024-08-18 22:42",
      "link": "http://xlwlgzs.com/archives/mian-fei-da-xue-bi-bei-ji-suan-ji-er-ji-zi-liao-lai-la-~",
      "author": "小陆yaの博客",
      "avatar": "https://cdn.qyliu.top/i/2024/08/18/66c1b740ad40d.webp"
    },
    {
      "title": "八奈见杏菜卡路里摄入统计",
      "created": "2024-08-15 23:07",
      "link": "https://www.himiku.com/archives/yanami-calorie-meter.html",
      "author": "初之音",
      "avatar": "https://cravatar.cn/avatar/2fc4cf3560ff5a1cc64ea029896ab235?s=400"
    },
    {
      "title": "Windows11 重装小记",
      "created": "2024-08-10 18:21",
      "link": "https://www.himiku.com/archives/reinstall-windows-11.html",
      "author": "初之音",
      "avatar": "https://cravatar.cn/avatar/2fc4cf3560ff5a1cc64ea029896ab235?s=400"
    },
    {
      "title": "在群晖上部署一个私有化聊天工具",
      "created": "2024-08-09 01:27",
      "link": "https://www.lxink.cn/posts/10e44716.html",
      "author": "凉心",
      "avatar": "https://cdn.qyliu.top/i/2024/05/24/66500d797ac38.png"
    },
    {
      "title": "装机必备佳软（持续更新中…）",
      "created": "2024-08-04 19:47",
      "link": "https://gyhwd.top/archives/ArlNkj6O",
      "author": "青竹小轩",
      "avatar": "https://cdn.qyliu.top/i/2024/04/23/662748990165a.png"
    },
    {
      "title": "Serv00部署Memos",
      "created": "2024-08-03 19:23",
      "link": "https://www.gan1ser.top/post/6a236522.html",
      "author": "GanSer",
      "avatar": "https://cdn.qyliu.top/i/2024/04/29/662fbba91addc.png"
    },
    {
      "title": "通过Webdav给群晖挂载115网盘",
      "created": "2024-07-27 21:06",
      "link": "https://www.lxink.cn/posts/1d46e004.html",
      "author": "凉心",
      "avatar": "https://cdn.qyliu.top/i/2024/05/24/66500d797ac38.png"
    },
    {
      "title": "Over the Wire - [01]Bandit (3)",
      "created": "2024-07-27 08:00",
      "link": "https://cworld0.com/blog/over-the-wire-bandit-3",
      "author": "CWorld",
      "avatar": "https://cdn.qyliu.top/i/2024/11/18/673b5d44a04dd.webp"
    },
    {
      "title": "HelloGitHub 第 100 期",
      "created": "2024-07-26 08:04",
      "link": "https://hellogithub.com/periodical/volume/100",
      "author": "hellogithub",
      "avatar": "https://cravatar.cn/avatar/f2134513983f3f5225d92b2c07da758c?d=mp&s=80"
    },
    {
      "title": "最近折腾群晖那点事",
      "created": "2024-07-13 23:07",
      "link": "https://www.lxink.cn/posts/b7c76dae.html",
      "author": "凉心",
      "avatar": "https://cdn.qyliu.top/i/2024/05/24/66500d797ac38.png"
    },
    {
      "title": "信盈达实习记录",
      "created": "2024-07-07 17:13",
      "link": "https://www.gan1ser.top/post/754a429b.html",
      "author": "GanSer",
      "avatar": "https://cdn.qyliu.top/i/2024/04/29/662fbba91addc.png"
    },
    {
      "title": "数字信号的2FSK调制与解调",
      "created": "2024-06-27 04:13",
      "link": "https://www.gan1ser.top/post/b9a95f5e.html",
      "author": "GanSer",
      "avatar": "https://cdn.qyliu.top/i/2024/04/29/662fbba91addc.png"
    },
    {
      "title": "Cloudreve捐助版Docker部署指南",
      "created": "2024-06-23 18:15",
      "link": "https://www.lxink.cn/posts/73544047.html",
      "author": "凉心",
      "avatar": "https://cdn.qyliu.top/i/2024/05/24/66500d797ac38.png"
    },
    {
      "title": "java生成15位流水号保证不重复",
      "created": "2024-04-25 09:42",
      "link": "https://www.liuyg.cn/archives/1714008473494",
      "author": "javaLYG",
      "avatar": "https://www.liuyg.cn/icon.png"
    },
    {
      "title": "幻兽帕鲁服务器搭建教程，腾讯云配置幻兽帕鲁服务器超简单教程",
      "created": "2024-01-26 13:07",
      "link": "https://www.liuyg.cn/archives/1706244220458",
      "author": "javaLYG",
      "avatar": "https://www.liuyg.cn/icon.png"
    },
    {
      "title": "mysql表空间整理",
      "created": "2024-01-17 11:29",
      "link": "https://www.liuyg.cn/archives/1705461770043",
      "author": "javaLYG",
      "avatar": "https://www.liuyg.cn/icon.png"
    },
    {
      "title": "引入jar包提示Invalid bound statement (not found)绑定不到jar中的mapper",
      "created": "2023-12-20 11:00",
      "link": "https://www.liuyg.cn/archives/1703040831683",
      "author": "javaLYG",
      "avatar": "https://www.liuyg.cn/icon.png"
    }
  ]
}